README.txt
setup.cfg
setup.py
collective/__init__.py
collective.googlesharing.egg-info/PKG-INFO
collective.googlesharing.egg-info/SOURCES.txt
collective.googlesharing.egg-info/dependency_links.txt
collective.googlesharing.egg-info/entry_points.txt
collective.googlesharing.egg-info/namespace_packages.txt
collective.googlesharing.egg-info/not-zip-safe
collective.googlesharing.egg-info/requires.txt
collective.googlesharing.egg-info/top_level.txt
collective/googlesharing/LICENSE
collective/googlesharing/__init__.py
collective/googlesharing/configure.zcml
collective/googlesharing/tests.py
collective/googlesharing/browser/GDataSharing.py
collective/googlesharing/browser/__init__.py
collective/googlesharing/browser/configure.zcml
collective/googlesharing/browser/googlesharing.pt
collective/googlesharing/browser/googlesharing.py
docs/HISTORY.txt
docs/INSTALL.txt
docs/LICENSE.GPL
docs/LICENSE.txt