Metadata-Version: 1.0
Name: collective.googlesharing
Version: 1.0.0
Summary: GS manages the sharing of documents stored in the Google servers and their synchronization from the Plone application to Google Docs service
Home-page: http://svn.plone.org/svn/collective/collective.googlesharing/
Author: D'Elia Federica
Author-email: federica.delia@redturtle.it
License: GPL
Keywords: plone google googledocs
Platform: UNKNOWN
Classifier: Framework :: Plone
Classifier: Programming Language :: Python
Classifier: Topic :: Software Development :: Libraries :: Python Modules
